dbt/adapters/starrocks/__init__.py
dbt/adapters/starrocks/__version__.py
dbt/adapters/starrocks/column.py
dbt/adapters/starrocks/connections.py
dbt/adapters/starrocks/impl.py
dbt/adapters/starrocks/relation.py
dbt/include/starrocks/__init__.py
dbt/include/starrocks/dbt_project.yml
dbt/include/starrocks/profile_template.yml
dbt/include/starrocks/sample_profiles.yml
dbt/include/starrocks/macros/adapters/columns.sql
dbt/include/starrocks/macros/adapters/freshness.sql
dbt/include/starrocks/macros/adapters/metadata.sql
dbt/include/starrocks/macros/adapters/relation.sql
dbt/include/starrocks/macros/adapters/relation_helpers.sql
dbt/include/starrocks/macros/adapters/schema.sql
dbt/include/starrocks/macros/get_custom_name/get_custom_database.sql
dbt/include/starrocks/macros/materializations/models/table/create_table_as.sql
dbt/include/starrocks/macros/materializations/models/view/create_view_as.sql
dbt/include/starrocks/macros/materializations/seeds/helpers.sql
dbt/include/starrocks/macros/materializations/snapshots/snapshot.sql
dbt/include/starrocks/macros/materializations/snapshots/snapshot_merge.sql
dbt/include/starrocks/macros/materializations/snapshots/strategies.sql
dbt_dataops_starrocks-1.4.3.dist-info/LICENSE.txt
dbt_dataops_starrocks-1.4.3.dist-info/METADATA
dbt_dataops_starrocks-1.4.3.dist-info/WHEEL
dbt_dataops_starrocks-1.4.3.dist-info/top_level.txt
dbt_dataops_starrocks-1.4.3.dist-info/RECORD
