Metadata-Version: 2.1
Name: dbt-dataops-starrocks
Version: 1.4.3
Summary: The starrocks adapter plugin for dbt
Home-page: https://github.com/StarRocks/starrocks/tree/main/contrib/dbt-connector
Author: fujianhj, long2ice
Author-email: fujianhj@gmail.com, long2ice@gmail.com
License: Apache License 2.0
Platform: any
Classifier: Development Status :: 5 - Production/Stable
Classifier: License :: OSI Approved :: Apache Software License
Classifier: Operating System :: Microsoft :: Windows
Classifier: Operating System :: MacOS :: MacOS X
Classifier: Operating System :: POSIX :: Linux
Classifier: Programming Language :: Python :: 3.7
Classifier: Programming Language :: Python :: 3.8
Classifier: Programming Language :: Python :: 3.9
Classifier: Programming Language :: Python :: 3.10
Classifier: Programming Language :: Python :: 3.11
Requires-Python: >=3.7
License-File: LICENSE.txt
Requires-Dist: dbt-core (==1.4.1)
Requires-Dist: mysql-connector-python (==8.0.29)
Requires-Dist: pytz (==2022.7.1)
